git_clone_stats/__init__.py
git_clone_stats/app.py
git_clone_stats/cli.py
git_clone_stats/db_factory.py
git_clone_stats/firestore_db.py
git_clone_stats/models.py
git_clone_stats/server.py
git_clone_stats/server_db_adapter.py
git_clone_stats/static/index.html
git_clone_stats/static/repo-card-template.html
git_clone_stats/static/script.js
git_clone_stats/static/styles.css
git_clone_stats-1.0.6.data/data/git_clone_stats/static/index.html
git_clone_stats-1.0.6.data/data/git_clone_stats/static/repo-card-template.html
git_clone_stats-1.0.6.data/data/git_clone_stats/static/script.js
git_clone_stats-1.0.6.data/data/git_clone_stats/static/styles.css
git_clone_stats-1.0.6.dist-info/METADATA
git_clone_stats-1.0.6.dist-info/WHEEL
git_clone_stats-1.0.6.dist-info/entry_points.txt
git_clone_stats-1.0.6.dist-info/licenses/LICENSE
git_clone_stats-1.0.6.dist-info/RECORD
