Metadata-Version: 2.4
Name: git-clone-stats
Version: 1.0.6
Summary: GitHub repository clone statistics tracker with web dashboard
Project-URL: Homepage, https://github.com/taylorwilsdon/git-clone-stats
Project-URL: Repository, https://github.com/taylorwilsdon/git-clone-stats
Project-URL: Issues, https://github.com/taylorwilsdon/git-clone-stats/issues
Project-URL: Documentation, https://github.com/taylorwilsdon/git-clone-stats#readme
Author-email: Taylor Wilsdon <taylor@example.com>
License-Expression: MIT
License-File: LICENSE
Keywords: analytics,clone-tracking,dashboard,github,statistics
Classifier: Development Status :: 4 - Beta
Classifier: Environment :: Console
Classifier: Environment :: Web Environment
Classifier: Intended Audience :: Developers
Classifier: License :: OSI Approved :: MIT License
Classifier: Operating System :: OS Independent
Classifier: Programming Language :: Python :: 3
Classifier: Programming Language :: Python :: 3.8
Classifier: Programming Language :: Python :: 3.9
Classifier: Programming Language :: Python :: 3.10
Classifier: Programming Language :: Python :: 3.11
Classifier: Programming Language :: Python :: 3.12
Classifier: Topic :: Internet :: WWW/HTTP :: HTTP Servers
Classifier: Topic :: Software Development :: Libraries :: Python Modules
Classifier: Topic :: System :: Monitoring
Requires-Python: >=3.8
Requires-Dist: requests>=2.25.0
Provides-Extra: dev
Requires-Dist: black>=22.0; extra == 'dev'
Requires-Dist: flake8>=4.0; extra == 'dev'
Requires-Dist: isort>=5.0; extra == 'dev'
Requires-Dist: mypy>=0.900; extra == 'dev'
Requires-Dist: pytest>=6.0; extra == 'dev'
